[
    {
        "Catalog":  "Windows Server 20H2",
        "OSDVersion":  "22.7.12.1",
        "OSDStatus":  "",
        "UpdateOS":  "Windows Server",
        "UpdateBuild":  "20H2",
        "UpdateArch":  "x64",
        "UpdateGroup":  "AdobeSU",
        "CreationDate":  "\/Date(1613512806000)\/",
        "KBNumber":  "4577586",
        "FileKBNumber":  "4577586",
        "Title":  "Update for Removal of Adobe Flash Player for Windows Server version 20H2 for x64-based systems (KB4577586)",
        "UpdateId":  "20bd2d6b-26a9-4ddd-8a3f-04a79b683c1f",
        "LegacyName":  "KB4577586-Windows1020h2Server-RTM-X64-TSL-World",
        "Type":  "SelfContained",
        "FileName":  "Windows10.0-KB4577586-x64.cab",
        "Size":  21321,
        "CompanyTitles":  "Microsoft",
        "ProductFamilyTitles":  "Windows",
        "Category":  "Windows Server, version 1903 and later",
        "UpdateClassificationTitle":  "Updates",
        "MsrcSeverity":  "Unspecified",
        "SecurityBulletins":  "",
        "UpdateType":  "Software",
        "PublicationState":  "Published",
        "HasLicenseAgreement":  false,
        "RequiresLicenseAgreementAcceptance":  false,
        "State":  "Ready",
        "IsLatestRevision":  true,
        "HasEarlierRevision":  false,
        "IsBeta":  false,
        "HasStaleUpdateApprovals":  false,
        "IsApproved":  false,
        "IsDeclined":  false,
        "HasSupersededUpdates":  false,
        "IsSuperseded":  false,
        "IsWsusInfrastructureUpdate":  false,
        "IsEditable":  false,
        "UpdateSource":  "MicrosoftUpdate",
        "AdditionalInformationUrls":  "https://support.microsoft.com/help/4577586",
        "Description":  "This update will remove Adobe Flash Player from your Windows machine. After you install this item, you may have to restart your computer.",
        "ReleaseNotes":  "",
        "FileUri":  "http://download.windowsupdate.com/c/msdownload/update/software/updt/2020/10/windows10.0-kb4577586-x64_025c603f506481a321d52e47e18fe8374b64a3a5.cab",
        "OriginUri":  "http://download.windowsupdate.com/c/msdownload/update/software/updt/2020/10/windows10.0-kb4577586-x64_025c603f506481a321d52e47e18fe8374b64a3a5.cab",
        "Hash":  "2 92 96 63 80 100 129 163 33 213 46 71 225 143 232 55 75 100 163 165",
        "AdditionalHash":  "89 182 148 163 5 79 30 154 106 201 31 87 1 240 43 143 219 6 67 105 111 57 44 226 230 44 246 198 191 104 123 153",
        "OSDCore":  "",
        "OSDWinPE":  "",
        "OSDGuid":  "522aa624-5b11-4dc7-b940-11f480b777d9",
        "PartitionKey":  "Windows Server 20H2",
        "RowKey":  "522aa624-5b11-4dc7-b940-11f480b777d9"
    },
    {
        "Catalog":  "Windows Server 20H2",
        "OSDVersion":  "22.7.12.1",
        "OSDStatus":  "",
        "UpdateOS":  "Windows Server",
        "UpdateBuild":  "20H2",
        "UpdateArch":  "x64",
        "UpdateGroup":  "Optional",
        "CreationDate":  "\/Date(1615327326000)\/",
        "KBNumber":  "4589212",
        "FileKBNumber":  "4589212",
        "Title":  "2021-01 Update for Windows Server version 20H2 for x64-based Systems (KB4589212)",
        "UpdateId":  "2964d7dd-8ba6-4c3e-992c-e154a1008cce",
        "LegacyName":  "KB4589212-Windows1020h2Server-RTM-X64-TSL-World",
        "Type":  "SelfContained",
        "FileName":  "Windows10.0-KB4589212-v2-x64.cab",
        "Size":  3122038,
        "CompanyTitles":  "Microsoft",
        "ProductFamilyTitles":  "Windows",
        "Category":  "Windows Server, version 1903 and later",
        "UpdateClassificationTitle":  "Updates",
        "MsrcSeverity":  "Unspecified",
        "SecurityBulletins":  "",
        "UpdateType":  "Software",
        "PublicationState":  "Published",
        "HasLicenseAgreement":  false,
        "RequiresLicenseAgreementAcceptance":  false,
        "State":  "Ready",
        "IsLatestRevision":  true,
        "HasEarlierRevision":  false,
        "IsBeta":  false,
        "HasStaleUpdateApprovals":  false,
        "IsApproved":  false,
        "IsDeclined":  false,
        "HasSupersededUpdates":  false,
        "IsSuperseded":  false,
        "IsWsusInfrastructureUpdate":  false,
        "IsEditable":  false,
        "UpdateSource":  "MicrosoftUpdate",
        "AdditionalInformationUrls":  "https://support.microsoft.com/help/4589212",
        "Description":  "Install this update to resolve issues in Windows. For a complete listing of the issues that are included in this update, see the associated Microsoft Knowledge Base article for more information. After you install this item, you may have to restart your computer.",
        "ReleaseNotes":  "",
        "FileUri":  "http://download.windowsupdate.com/c/msdownload/update/software/updt/2021/01/windows10.0-kb4589212-v2-x64_a2aabdd9d06d57c9275997cab64eb45d6821e934.cab",
        "OriginUri":  "http://download.windowsupdate.com/c/msdownload/update/software/updt/2021/01/windows10.0-kb4589212-v2-x64_a2aabdd9d06d57c9275997cab64eb45d6821e934.cab",
        "Hash":  "162 170 189 217 208 109 87 201 39 89 151 202 182 78 180 93 104 33 233 52",
        "AdditionalHash":  "105 149 50 78 234 243 222 76 117 96 156 226 38 135 72 99 236 246 105 212 119 48 40 43 79 233 162 92 212 190 240 76",
        "OSDCore":  "",
        "OSDWinPE":  "",
        "OSDGuid":  "a065fd83-7693-4c89-980f-097a7705ba51",
        "PartitionKey":  "Windows Server 20H2",
        "RowKey":  "a065fd83-7693-4c89-980f-097a7705ba51"
    },
    {
        "Catalog":  "Windows Server 20H2",
        "OSDVersion":  "22.7.12.1",
        "OSDStatus":  "",
        "UpdateOS":  "Windows Server",
        "UpdateBuild":  "20H2",
        "UpdateArch":  "x64",
        "UpdateGroup":  "SSU",
        "CreationDate":  "\/Date(1628614806000)\/",
        "KBNumber":  "5005260",
        "FileKBNumber":  "19041 1161",
        "Title":  "2021-08 Servicing Stack Update for Windows Server version 20H2 for x64-based Systems (KB5005260)",
        "UpdateId":  "389107ad-d49e-4725-9ce5-93f3cd89e216",
        "LegacyName":  "KB5005260-Windows1020h2Server-RTM-ServicingStackUpdate-X64-TSL-World",
        "Type":  "SelfContained",
        "FileName":  "SSU-19041.1161-x64.cab",
        "Size":  15362985,
        "CompanyTitles":  "Microsoft",
        "ProductFamilyTitles":  "Windows",
        "Category":  "Windows Server, version 1903 and later",
        "UpdateClassificationTitle":  "Security Updates",
        "MsrcSeverity":  "Critical",
        "SecurityBulletins":  "",
        "UpdateType":  "Software",
        "PublicationState":  "Published",
        "HasLicenseAgreement":  false,
        "RequiresLicenseAgreementAcceptance":  false,
        "State":  "Ready",
        "IsLatestRevision":  true,
        "HasEarlierRevision":  false,
        "IsBeta":  false,
        "HasStaleUpdateApprovals":  false,
        "IsApproved":  false,
        "IsDeclined":  false,
        "HasSupersededUpdates":  true,
        "IsSuperseded":  false,
        "IsWsusInfrastructureUpdate":  false,
        "IsEditable":  false,
        "UpdateSource":  "MicrosoftUpdate",
        "AdditionalInformationUrls":  "https://support.microsoft.com/help/5005260",
        "Description":  "Install this update to resolve issues in Windows. For a complete listing of the issues that are included in this update, see the associated Microsoft Knowledge Base article for more information. After you install this item, you may have to restart your computer.",
        "ReleaseNotes":  "",
        "FileUri":  "http://download.windowsupdate.com/d/msdownload/update/software/secu/2021/08/ssu-19041.1161-x64_7c0b02b7c1c2419ca955f7a4a4ab3f316dce6e23.cab",
        "OriginUri":  "http://download.windowsupdate.com/d/msdownload/update/software/secu/2021/08/ssu-19041.1161-x64_7c0b02b7c1c2419ca955f7a4a4ab3f316dce6e23.cab",
        "Hash":  "124 11 2 183 193 194 65 156 169 85 247 164 164 171 63 49 109 206 110 35",
        "AdditionalHash":  "82 36 173 110 141 157 46 145 171 222 203 216 195 166 161 41 193 234 1 180 52 216 52 28 135 49 151 168 99 186 83 174",
        "OSDCore":  "",
        "OSDWinPE":  "",
        "OSDGuid":  "311bec29-7505-4849-bebf-21f2f55dcb8a",
        "PartitionKey":  "Windows Server 20H2",
        "RowKey":  "311bec29-7505-4849-bebf-21f2f55dcb8a"
    },
    {
        "Catalog":  "Windows Server 20H2",
        "OSDVersion":  "22.7.12.1",
        "OSDStatus":  "",
        "UpdateOS":  "Windows Server",
        "UpdateBuild":  "20H2",
        "UpdateArch":  "x64",
        "UpdateGroup":  "DotNetCU",
        "CreationDate":  "\/Date(1652202000000)\/",
        "KBNumber":  "5013624",
        "FileKBNumber":  "5013624",
        "Title":  "2022-05 Cumulative Update for .NET Framework 3.5 and 4.8 for Windows Server version 20H2 for x64 (KB5013624)",
        "UpdateId":  "7e1c56be-04f1-4981-85b0-f69b39957bd7",
        "LegacyName":  "KB5013624-DotNetCumulative-20H2-Server-x64-Retail",
        "Type":  "SelfContained",
        "FileName":  "Windows10.0-KB5013624-x64-NDP48.cab",
        "Size":  69557880,
        "CompanyTitles":  "Microsoft",
        "ProductFamilyTitles":  "Windows",
        "Category":  "Windows Server, version 1903 and later",
        "UpdateClassificationTitle":  "Security Updates",
        "MsrcSeverity":  "Important",
        "SecurityBulletins":  "",
        "UpdateType":  "Software",
        "PublicationState":  "Published",
        "HasLicenseAgreement":  false,
        "RequiresLicenseAgreementAcceptance":  false,
        "State":  "Ready",
        "IsLatestRevision":  true,
        "HasEarlierRevision":  false,
        "IsBeta":  false,
        "HasStaleUpdateApprovals":  false,
        "IsApproved":  false,
        "IsDeclined":  false,
        "HasSupersededUpdates":  true,
        "IsSuperseded":  false,
        "IsWsusInfrastructureUpdate":  false,
        "IsEditable":  false,
        "UpdateSource":  "MicrosoftUpdate",
        "AdditionalInformationUrls":  "http://support.microsoft.com/kb/5013624",
        "Description":  "A security issue has been identified in a Microsoft software product that could affect your system. You can help protect your system by installing this update from Microsoft. For a complete listing of the issues that are included in this update, see the associated Microsoft Knowledge Base article. After you install this update, you may have to restart your system.",
        "ReleaseNotes":  "",
        "FileUri":  "http://download.windowsupdate.com/c/msdownload/update/software/secu/2022/04/windows10.0-kb5013624-x64-ndp48_6f79154c6a693ba11ccaf009e3f65c70ccbda282.cab",
        "OriginUri":  "http://download.windowsupdate.com/c/msdownload/update/software/secu/2022/04/windows10.0-kb5013624-x64-ndp48_6f79154c6a693ba11ccaf009e3f65c70ccbda282.cab",
        "Hash":  "111 121 21 76 106 105 59 161 28 202 240 9 227 246 92 112 204 189 162 130",
        "AdditionalHash":  "33 157 140 14 33 244 108 11 170 86 213 251 54 141 45 98 55 2 2 196 188 183 115 21 59 223 48 240 4 38 61 209",
        "OSDCore":  "",
        "OSDWinPE":  "",
        "OSDGuid":  "abc3478d-c738-40a3-bb4e-24a197caceb7",
        "PartitionKey":  "Windows Server 20H2",
        "RowKey":  "abc3478d-c738-40a3-bb4e-24a197caceb7"
    },
    {
        "Catalog":  "Windows Server 20H2",
        "OSDVersion":  "22.7.12.1",
        "OSDStatus":  "",
        "UpdateOS":  "Windows Server",
        "UpdateBuild":  "20H2",
        "UpdateArch":  "x64",
        "UpdateGroup":  "SSU",
        "CreationDate":  "\/Date(1652202126000)\/",
        "KBNumber":  "5014032",
        "FileKBNumber":  "19041 1704",
        "Title":  "2022-05 Servicing Stack Update for Windows Server version 20H2 for x64-based Systems (KB5014032)",
        "UpdateId":  "e9824705-ba15-4183-b1af-3c8c8ff5f1c6",
        "LegacyName":  "KB5014032-Windows1020h2Server-RTM-ServicingStackUpdate-X64-TSL-World",
        "Type":  "SelfContained",
        "FileName":  "SSU-19041.1704-x64.cab",
        "Size":  15671025,
        "CompanyTitles":  "Microsoft",
        "ProductFamilyTitles":  "Windows",
        "Category":  "Windows Server, version 1903 and later",
        "UpdateClassificationTitle":  "Security Updates",
        "MsrcSeverity":  "Critical",
        "SecurityBulletins":  "",
        "UpdateType":  "Software",
        "PublicationState":  "Published",
        "HasLicenseAgreement":  false,
        "RequiresLicenseAgreementAcceptance":  false,
        "State":  "Ready",
        "IsLatestRevision":  true,
        "HasEarlierRevision":  false,
        "IsBeta":  false,
        "HasStaleUpdateApprovals":  false,
        "IsApproved":  false,
        "IsDeclined":  false,
        "HasSupersededUpdates":  true,
        "IsSuperseded":  false,
        "IsWsusInfrastructureUpdate":  false,
        "IsEditable":  false,
        "UpdateSource":  "MicrosoftUpdate",
        "AdditionalInformationUrls":  "https://support.microsoft.com/help/5014032",
        "Description":  "Install this update to resolve issues in Windows. For a complete listing of the issues that are included in this update, see the associated Microsoft Knowledge Base article for more information. After you install this item, you may have to restart your computer.",
        "ReleaseNotes":  "",
        "FileUri":  "http://download.windowsupdate.com/c/msdownload/update/software/secu/2022/05/ssu-19041.1704-x64_c01ad66716dc695d7aa1afab622e2d8be0eb2d65.cab",
        "OriginUri":  "http://download.windowsupdate.com/c/msdownload/update/software/secu/2022/05/ssu-19041.1704-x64_c01ad66716dc695d7aa1afab622e2d8be0eb2d65.cab",
        "Hash":  "192 26 214 103 22 220 105 93 122 161 175 171 98 46 45 139 224 235 45 101",
        "AdditionalHash":  "245 122 50 15 38 85 33 65 29 17 50 107 95 44 165 204 197 167 111 138 83 47 198 106 195 181 128 115 157 0 229 251",
        "OSDCore":  "",
        "OSDWinPE":  "",
        "OSDGuid":  "2975f251-76a5-41dc-86a8-69181f4cd8c3",
        "PartitionKey":  "Windows Server 20H2",
        "RowKey":  "2975f251-76a5-41dc-86a8-69181f4cd8c3"
    },
    {
        "Catalog":  "Windows Server 20H2",
        "OSDVersion":  "22.7.12.1",
        "OSDStatus":  "",
        "UpdateOS":  "Windows Server",
        "UpdateBuild":  "20H2",
        "UpdateArch":  "x64",
        "UpdateGroup":  "DotNetCU",
        "CreationDate":  "\/Date(1655226000000)\/",
        "KBNumber":  "5013887",
        "FileKBNumber":  "5013887",
        "Title":  "2022-06 Cumulative Update for .NET Framework 3.5 and 4.8 for Windows Server version 20H2 for x64 (KB5013887)",
        "UpdateId":  "af93b63d-c15e-44a7-84e0-ac944c464179",
        "LegacyName":  "KB5013887-DotNetCumulative-20H2-Server-x64-Retail",
        "Type":  "SelfContained",
        "FileName":  "Windows10.0-KB5013887-x64-NDP48.cab",
        "Size":  70356524,
        "CompanyTitles":  "Microsoft",
        "ProductFamilyTitles":  "Windows",
        "Category":  "Windows Server, version 1903 and later",
        "UpdateClassificationTitle":  "Updates",
        "MsrcSeverity":  "Unspecified",
        "SecurityBulletins":  "",
        "UpdateType":  "Software",
        "PublicationState":  "Published",
        "HasLicenseAgreement":  false,
        "RequiresLicenseAgreementAcceptance":  false,
        "State":  "Ready",
        "IsLatestRevision":  true,
        "HasEarlierRevision":  false,
        "IsBeta":  false,
        "HasStaleUpdateApprovals":  false,
        "IsApproved":  false,
        "IsDeclined":  false,
        "HasSupersededUpdates":  true,
        "IsSuperseded":  false,
        "IsWsusInfrastructureUpdate":  false,
        "IsEditable":  false,
        "UpdateSource":  "MicrosoftUpdate",
        "AdditionalInformationUrls":  "http://support.microsoft.com/kb/5013887",
        "Description":  "Install this update to resolve issues in Windows. For a complete listing of the issues that are included in this update, see the associated Microsoft Knowledge Base article for more information. After you install this item, you may have to restart your computer.",
        "ReleaseNotes":  "",
        "FileUri":  "http://download.windowsupdate.com/d/msdownload/update/software/updt/2022/04/windows10.0-kb5013887-x64-ndp48_aa0da938276607c9736d87066ade1776dafd7aa5.cab",
        "OriginUri":  "http://download.windowsupdate.com/d/msdownload/update/software/updt/2022/04/windows10.0-kb5013887-x64-ndp48_aa0da938276607c9736d87066ade1776dafd7aa5.cab",
        "Hash":  "170 13 169 56 39 102 7 201 115 109 135 6 106 222 23 118 218 253 122 165",
        "AdditionalHash":  "157 1 148 63 245 141 83 200 193 45 161 204 230 188 167 2 118 9 63 1 253 137 61 127 109 82 103 230 49 57 237 148",
        "OSDCore":  "",
        "OSDWinPE":  "",
        "OSDGuid":  "d63c6912-d450-49d8-9c6f-559e016c76ad",
        "PartitionKey":  "Windows Server 20H2",
        "RowKey":  "d63c6912-d450-49d8-9c6f-559e016c76ad"
    },
    {
        "Catalog":  "Windows Server 20H2",
        "OSDVersion":  "22.7.12.1",
        "OSDStatus":  "",
        "UpdateOS":  "Windows Server",
        "UpdateBuild":  "20H2",
        "UpdateArch":  "x64",
        "UpdateGroup":  "LCU",
        "CreationDate":  "\/Date(1657645207000)\/",
        "KBNumber":  "5015807",
        "FileKBNumber":  "5015807",
        "Title":  "2022-07 Cumulative Update for Windows Server version 20H2 for x64-based Systems (KB5015807)",
        "UpdateId":  "51c1eea0-5bd0-4188-9068-04cc6177eb33",
        "LegacyName":  "KB5015807-Windows1020h2Server-RTM-UnifiedCumulativeSecurity-X64-TSL-World",
        "Type":  "SelfContained",
        "FileName":  "Windows10.0-KB5015807-x64.cab",
        "Size":  710737992,
        "CompanyTitles":  "Microsoft",
        "ProductFamilyTitles":  "Windows",
        "Category":  "Windows Server, version 1903 and later",
        "UpdateClassificationTitle":  "Security Updates",
        "MsrcSeverity":  "Critical",
        "SecurityBulletins":  "",
        "UpdateType":  "Software",
        "PublicationState":  "Published",
        "HasLicenseAgreement":  false,
        "RequiresLicenseAgreementAcceptance":  false,
        "State":  "Ready",
        "IsLatestRevision":  true,
        "HasEarlierRevision":  false,
        "IsBeta":  false,
        "HasStaleUpdateApprovals":  false,
        "IsApproved":  false,
        "IsDeclined":  false,
        "HasSupersededUpdates":  true,
        "IsSuperseded":  false,
        "IsWsusInfrastructureUpdate":  false,
        "IsEditable":  false,
        "UpdateSource":  "MicrosoftUpdate",
        "AdditionalInformationUrls":  "https://support.microsoft.com/help/5015807",
        "Description":  "Install this update to resolve issues in Windows. For a complete listing of the issues that are included in this update, see the associated Microsoft Knowledge Base article for more information. After you install this item, you may have to restart your computer.",
        "ReleaseNotes":  "",
        "FileUri":  "http://download.windowsupdate.com/d/msdownload/update/software/secu/2022/07/windows10.0-kb5015807-x64_a907dd21ee0bab05848382eccf2fc802b2b0831a.cab",
        "OriginUri":  "http://download.windowsupdate.com/d/msdownload/update/software/secu/2022/07/windows10.0-kb5015807-x64_a907dd21ee0bab05848382eccf2fc802b2b0831a.cab",
        "Hash":  "169 7 221 33 238 11 171 5 132 131 130 236 207 47 200 2 178 176 131 26",
        "AdditionalHash":  "112 255 101 238 82 82 18 128 201 218 9 22 166 178 211 100 234 222 131 183 249 218 34 253 169 34 195 196 193 216 145 196",
        "OSDCore":  "",
        "OSDWinPE":  "",
        "OSDGuid":  "18ccea09-ee7c-4d3b-9aca-602db9ea9740",
        "PartitionKey":  "Windows Server 20H2",
        "RowKey":  "18ccea09-ee7c-4d3b-9aca-602db9ea9740"
    }
]
