[
    {
        "Catalog":  "Windows 11 Dynamic Update",
        "OSDVersion":  "22.4.12.1",
        "OSDStatus":  "",
        "UpdateOS":  "Windows 11",
        "UpdateBuild":  "21H2",
        "UpdateArch":  "x64",
        "UpdateGroup":  "ComponentDU Critical",
        "CreationDate":  "\/Date(1637618406000)\/",
        "KBNumber":  "5007575",
        "FileKBNumber":  "5007575",
        "Title":  "2021-11 Dynamic Update for Windows 11 for x64-based Systems (KB5007575)",
        "UpdateId":  "0543c571-2166-4c6e-a7f5-fc888a9a6d96",
        "LegacyName":  "KB5007575-WindowsSV21H2-RTM-CriticalDU-X64-TSL-World",
        "Type":  "None",
        "FileName":  "Windows10.0-KB5007575-x64.cab",
        "Size":  278378,
        "CompanyTitles":  "Microsoft",
        "ProductFamilyTitles":  "Windows",
        "Category":  "Windows 11 Dynamic Update",
        "UpdateClassificationTitle":  "Critical Updates",
        "MsrcSeverity":  "Unspecified",
        "SecurityBulletins":  "",
        "UpdateType":  "Software",
        "PublicationState":  "Published",
        "HasLicenseAgreement":  false,
        "RequiresLicenseAgreementAcceptance":  false,
        "State":  "Ready",
        "IsLatestRevision":  true,
        "HasEarlierRevision":  false,
        "IsBeta":  false,
        "HasStaleUpdateApprovals":  false,
        "IsApproved":  false,
        "IsDeclined":  false,
        "HasSupersededUpdates":  false,
        "IsSuperseded":  false,
        "IsWsusInfrastructureUpdate":  false,
        "IsEditable":  false,
        "UpdateSource":  "MicrosoftUpdate",
        "AdditionalInformationUrls":  "https://support.microsoft.com/help/5007575",
        "Description":  "ComponentUpdate:",
        "ReleaseNotes":  "",
        "FileUri":  "http://download.windowsupdate.com/d/msdownload/update/software/crup/2021/11/windows10.0-kb5007575-x64_28e206f7d3a99eb798dfa403e6439dfb5e358e16.cab",
        "OriginUri":  "http://download.windowsupdate.com/d/msdownload/update/software/crup/2021/11/windows10.0-kb5007575-x64_28e206f7d3a99eb798dfa403e6439dfb5e358e16.cab",
        "Hash":  "40 226 6 247 211 169 158 183 152 223 164 3 230 67 157 251 94 53 142 22",
        "AdditionalHash":  "246 112 156 191 92 0 242 235 183 206 70 93 235 237 144 148 102 49 219 250 226 190 14 141 197 25 168 142 20 146 220 240",
        "OSDCore":  "",
        "OSDWinPE":  "",
        "OSDGuid":  "696dc7be-8891-4091-89dc-43677d583ae7",
        "PartitionKey":  "Windows 11 Dynamic Update",
        "RowKey":  "696dc7be-8891-4091-89dc-43677d583ae7"
    },
    {
        "Catalog":  "Windows 11 Dynamic Update",
        "OSDVersion":  "22.4.12.1",
        "OSDStatus":  "",
        "UpdateOS":  "Windows 11",
        "UpdateBuild":  "21H2",
        "UpdateArch":  "x64",
        "UpdateGroup":  "SetupDU",
        "CreationDate":  "\/Date(1648501206000)\/",
        "KBNumber":  "5011576",
        "FileKBNumber":  "5011576",
        "Title":  "2022-03 Dynamic Update for Windows 11 for x64-based Systems (KB5011576)",
        "UpdateId":  "4538e311-560d-4d2d-a390-ca8b5c9e008a",
        "LegacyName":  "KB5011576-WindowsSV21H2-RTM-SetupDU-X64-TSL-World",
        "Type":  "None",
        "FileName":  "Windows10.0-KB5011576-x64.cab",
        "Size":  12058105,
        "CompanyTitles":  "Microsoft",
        "ProductFamilyTitles":  "Windows",
        "Category":  "Windows 11 Dynamic Update",
        "UpdateClassificationTitle":  "Critical Updates",
        "MsrcSeverity":  "Unspecified",
        "SecurityBulletins":  "",
        "UpdateType":  "Software",
        "PublicationState":  "Published",
        "HasLicenseAgreement":  false,
        "RequiresLicenseAgreementAcceptance":  false,
        "State":  "Ready",
        "IsLatestRevision":  true,
        "HasEarlierRevision":  false,
        "IsBeta":  false,
        "HasStaleUpdateApprovals":  false,
        "IsApproved":  false,
        "IsDeclined":  false,
        "HasSupersededUpdates":  true,
        "IsSuperseded":  false,
        "IsWsusInfrastructureUpdate":  false,
        "IsEditable":  false,
        "UpdateSource":  "MicrosoftUpdate",
        "AdditionalInformationUrls":  "https://support.microsoft.com/help/5011576",
        "Description":  "SetupUpdate:",
        "ReleaseNotes":  "",
        "FileUri":  "http://download.windowsupdate.com/c/msdownload/update/software/crup/2022/03/windows10.0-kb5011576-x64_0b1a754263578d73f1a8e4f1435d249a7c8af4ad.cab",
        "OriginUri":  "http://download.windowsupdate.com/c/msdownload/update/software/crup/2022/03/windows10.0-kb5011576-x64_0b1a754263578d73f1a8e4f1435d249a7c8af4ad.cab",
        "Hash":  "11 26 117 66 99 87 141 115 241 168 228 241 67 93 36 154 124 138 244 173",
        "AdditionalHash":  "99 219 106 124 223 70 105 159 67 53 195 193 242 99 192 209 150 251 145 238 171 106 54 130 194 177 242 42 149 221 140 191",
        "OSDCore":  "",
        "OSDWinPE":  "",
        "OSDGuid":  "b3dfea1a-c995-4d9d-9ae8-dd09bc5d21f8",
        "PartitionKey":  "Windows 11 Dynamic Update",
        "RowKey":  "b3dfea1a-c995-4d9d-9ae8-dd09bc5d21f8"
    },
    {
        "Catalog":  "Windows 11 Dynamic Update",
        "OSDVersion":  "22.4.12.1",
        "OSDStatus":  "",
        "UpdateOS":  "Windows 11",
        "UpdateBuild":  "21H2",
        "UpdateArch":  "x64",
        "UpdateGroup":  "ComponentDU SafeOS",
        "CreationDate":  "\/Date(1648501206000)\/",
        "KBNumber":  "5011579",
        "FileKBNumber":  "5011579",
        "Title":  "2022-03 Dynamic Update for Windows 11 for x64-based Systems (KB5011579)",
        "UpdateId":  "4161681b-ff0a-4d8d-85de-0020e1680ecd",
        "LegacyName":  "KB5011579-WindowsSV21H2-RTM-SafeOSDU-X64-TSL-World",
        "Type":  "None",
        "FileName":  "Windows10.0-KB5011579-x64.cab",
        "Size":  2072710,
        "CompanyTitles":  "Microsoft",
        "ProductFamilyTitles":  "Windows",
        "Category":  "Windows 11 Dynamic Update Windows Safe OS Dynamic Update",
        "UpdateClassificationTitle":  "Critical Updates",
        "MsrcSeverity":  "Unspecified",
        "SecurityBulletins":  "",
        "UpdateType":  "Software",
        "PublicationState":  "Published",
        "HasLicenseAgreement":  false,
        "RequiresLicenseAgreementAcceptance":  false,
        "State":  "Ready",
        "IsLatestRevision":  true,
        "HasEarlierRevision":  false,
        "IsBeta":  false,
        "HasStaleUpdateApprovals":  false,
        "IsApproved":  false,
        "IsDeclined":  false,
        "HasSupersededUpdates":  true,
        "IsSuperseded":  false,
        "IsWsusInfrastructureUpdate":  false,
        "IsEditable":  false,
        "UpdateSource":  "MicrosoftUpdate",
        "AdditionalInformationUrls":  "https://support.microsoft.com/help/5011579",
        "Description":  "ComponentUpdate:",
        "ReleaseNotes":  "",
        "FileUri":  "http://download.windowsupdate.com/c/msdownload/update/software/crup/2022/03/windows10.0-kb5011579-x64_b20914bd75d31a24276ccab37cec93d8592f7c01.cab",
        "OriginUri":  "http://download.windowsupdate.com/c/msdownload/update/software/crup/2022/03/windows10.0-kb5011579-x64_b20914bd75d31a24276ccab37cec93d8592f7c01.cab",
        "Hash":  "178 9 20 189 117 211 26 36 39 108 202 179 124 236 147 216 89 47 124 1",
        "AdditionalHash":  "24 183 77 233 90 241 156 157 80 100 252 113 213 128 230 171 242 182 247 44 231 222 65 34 67 38 154 40 88 160 12 24",
        "OSDCore":  "",
        "OSDWinPE":  "",
        "OSDGuid":  "d6ee456b-4741-4eb1-87cc-4429480df5e3",
        "PartitionKey":  "Windows 11 Dynamic Update",
        "RowKey":  "d6ee456b-4741-4eb1-87cc-4429480df5e3"
    }
]
