{
    "Title":  "2025-01 Safe OS Dynamic Update for Windows 11 Version 24H2 for arm64-based Systems (KB5053117)",
    "Id":  "5053117",
    "Architecture":  "ARM64",
    "Language":  "",
    "Hotfix":  null,
    "Description":  "This update makes improvements to the Windows Recovery Environment (WinRE) for Windows.",
    "LastModified":  "2025-01-28",
    "Size":  "5.3 MB",
    "Classification":  "Critical Updates",
    "SupportedProducts":  [
                              "Windows Safe OS Dynamic Update",
                              "Windows 10 and later Dynamic Update"
                          ],
    "MSRCNumber":  null,
    "MSRCSeverity":  "n/a",
    "RebootBehavior":  "Can request restart",
    "RequestsUserInput":  false,
    "ExclusiveInstall":  "",
    "NetworkRequired":  false,
    "UninstallNotes":  null,
    "UninstallSteps":  null,
    "UpdateId":  "c41cccfd-6919-4a0d-897d-26f5d090b40a",
    "Supersedes":  [
                       {
                           "KB":  "5043934",
                           "Description":  "2024-09 Safe OS Dynamic Update for Windows 11 Version 24H2 for arm64-based Systems (KB5043934)"
                       },
                       {
                           "KB":  "5041979",
                           "Description":  "2024-07 Safe OS Dynamic Update for Windows 11 Version 24H2 for arm64-based Systems (KB5041979)"
                       },
                       {
                           "KB":  "5046910",
                           "Description":  "2024-11 Safe OS Dynamic Update for Windows 11 Version 24H2 for arm64-based Systems (KB5046910)"
                       },
                       {
                           "KB":  "5041137",
                           "Description":  "2024-06 Safe OS Dynamic Update for Windows 11 Version 24H2 for arm64-based Systems (KB5041137)"
                       },
                       {
                           "KB":  "5050119",
                           "Description":  "2025-01 Safe OS Dynamic Update for Windows 11 Version 24H2 for arm64-based Systems (KB5050119)"
                       },
                       {
                           "KB":  "5044612",
                           "Description":  "2024-10 Safe OS Dynamic Update for Windows 11 Version 24H2 for arm64-based Systems (KB5044612)"
                       },
                       {
                           "KB":  "5041980",
                           "Description":  "2024-08 Safe OS Dynamic Update for Windows 11 Version 24H2 for arm64-based Systems (KB5041980)"
                       },
                       {
                           "KB":  "5043355",
                           "Description":  "2024-09 Safe OS Dynamic Update for Windows 11 Version 24H2 for arm64-based Systems (KB5043355)"
                       }
                   ],
    "SupersededBy":  {

                     },
    "Link":  "https://catalog.sf.dl.delivery.mp.microsoft.com/filestreamingservice/files/d1b3e3a6-d6cf-482e-a2cb-f55a5c4a3a05/public/windows11.0-kb5053117-arm64_e4200815e4f012838695ce0f302da38a93ed1703.cab",
    "InputObject":  "Windows 11 24H2 arm64"
}
