{
	"$schema" : "https://aka.ms/winget-packages.schema.2.0.json",

	"title": "OSD Created WinGet Export",
	"description": "ADK MDT",

	"WinGetVersion" : "1.2.10691",
	"CreationDate" : "2023-06-25T23:43:27.520-00:00",

	"Sources" : 
	[
		{
			"SourceDetails" : 
			{
				"Argument" : "https://storeedgefd.dsx.mp.microsoft.com/v9.0",
				"Identifier" : "StoreEdgeFD",
				"Name" : "msstore",
				"Type" : "Microsoft.Rest"
			},
			"Packages" : 
			[
				{
					"PackageIdentifier" : "9NBLGGH4TX22"
				}
			]
		},
		{
			"SourceDetails" : 
			{
				"Argument" : "https://winget.azureedge.net/cache",
				"Identifier" : "Microsoft.Winget.Source_8wekyb3d8bbwe",
				"Name" : "winget",
				"Type" : "Microsoft.PreIndexed.Package"
			},
			"Packages" : 
			[
				{
					"PackageIdentifier" : "Microsoft.WindowsADK",
					"Version" : "10.1.22621.1"
				},
				{
					"PackageIdentifier" : "Microsoft.ADKPEAddon",
					"Version" : "10.1.22621.1"
				},
				{
					"PackageIdentifier" : "Microsoft.DeploymentToolkit",
					"Version" : "6.3.8456.1000"
				},
				{
					"PackageIdentifier" : "Git.Git",
					"Version" : "2.41.0"
				},
				{
					"PackageIdentifier" : "GitHub.GitHubDesktop",
					"Version" : "3.2.3"
				},
				{
					"PackageIdentifier" : "Microsoft.VisualStudioCode",
					"Version" : "1.79.2"
				},
				{
					"PackageIdentifier" : "Google.Chrome",
					"Version" : "114.0.5735.134"
				},
				{
					"PackageIdentifier" : "Notepad++.Notepad++",
					"Version" : "8.5.4"
				},
				{
					"PackageIdentifier" : "7zip.7zip",
					"Version" : "22.01.00.0"
				}
			]
		}
	]
}